{
  "startedDateTime": "2022-04-27T08:27:32.061Z",
  "clientIPAddress": "20.231.125.35",
  "method": "GET",
  "url": "https://mockbin.com/requests/e1f45d32-c603-11ec-b59c-000d3a8fc63b",
  "httpVersion": "HTTP/1.1",
  "cookies": {},
  "headers": {
    "host": "mockbin.com",
    "connection": "close",
    "accept-encoding": "gzip",
    "x-forwarded-for": "20.231.125.35, 172.70.174.251",
    "cf-ray": "70262df54b2f828a-IAD",
    "x-forwarded-proto": "http",
    "cf-visitor": "{\"scheme\":\"https\"}",
    "user-agent": "curl/7.68.0",
    "accept": "*/*",
    "cf-connecting-ip": "20.231.125.35",
    "cdn-loop": "cloudflare",
    "x-request-id": "24c98cf8-2140-4e1e-8f26-4f5785d2d78a",
    "x-forwarded-port": "80",
    "via": "1.1 vegur",
    "connect-time": "0",
    "x-request-start": "1651048052056",
    "total-route-time": "0"
  },
  "queryString": {},
  "postData": {
    "mimeType": "application/octet-stream",
    "text": "",
    "params": []
  },
  "headersSize": 528,
  "bodySize": 0
}
