[{"id":2,"symbol":"AAPL","companyName":"Apple Inc.","exchangeShortName":"NASDAQ","marketCap":"2457615692206","sector":"Technology","industry":"Consumer Electronics","price":"155.33","rev1":"99429448408","rev2":"84470002074","rev3":"118367705499","rev4":"91711527085","lastEarningsFiscalQuarter":null},{"id":7,"symbol":"AMZN","companyName":"Amazon.com, Inc.","exchangeShortName":"NASDAQ","marketCap":"1036616877711","sector":"Consumer Cyclical","industry":"Internet Retail","price":"101.16","rev1":"131456040323","rev2":"121473629431","rev3":"150991184819","rev4":"118895426469","lastEarningsFiscalQuarter":null},{"id":3,"symbol":"MSFT","companyName":"Microsoft Corporation","exchangeShortName":"NASDAQ","marketCap":"2004764233236","sector":"Technology","industry":"Software—Infrastructure","price":"269.32","rev1":"49381925502","rev2":"54984723082","rev3":"53253175098","rev4":"52514316994","lastEarningsFiscalQuarter":null},{"id":14,"symbol":"NVDA","companyName":"NVIDIA Corporation","exchangeShortName":"NASDAQ","marketCap":"567278880000","sector":"Technology","industry":"Semiconductors","price":"227.64","rev1":"7737656444","rev2":"6710613564","rev3":"5949641490","rev4":"8388187332","lastEarningsFiscalQuarter":null},{"id":13,"symbol":"TSLA","companyName":"Tesla, Inc.","exchangeShortName":"NASDAQ","marketCap":"677876804567","sector":"Consumer Cyclical","industry":"Auto Manufacturers","price":"214.24","rev1":"23863628462","rev2":"16756961881","rev3":"21418266215","rev4":"18860968331","lastEarningsFiscalQuarter":null}]