[{"id":1,"symbol":"AAPL","companyName":"Apple Inc.","exchangeShortName":"NASDAQ","marketCap":"2062007795712","sector":"Technology","industry":"Consumer Electronics","price":"129.62","rev1":"100787231718","rev2":"91926858720","rev3":"126360658255","rev4":"83642789940","lastEarningsFiscalQuarter":null},{"id":5,"symbol":"AMZN","companyName":"Amazon.com, Inc.","exchangeShortName":"NASDAQ","marketCap":"878162411520","sector":"Consumer Cyclical","industry":"Internet Retail","price":"86.08","rev1":"129864691475","rev2":"138973561725","rev3":"120436153863","rev4":"125843986330","lastEarningsFiscalQuarter":null},{"id":2,"symbol":"MSFT","companyName":"Microsoft Corporation","exchangeShortName":"NASDAQ","marketCap":"1676733972480","sector":"Technology","industry":"Software—Infrastructure","price":"224.93","rev1":"52334188631","rev2":"51432215569","rev3":"50298746370","rev4":"52636607434","lastEarningsFiscalQuarter":null}]