[{"id":1,"symbol":"AAPL","companyName":"Apple Inc.","exchangeShortName":"NASDAQ","marketCap":"2183336820736","sector":"Technology","industry":"Consumer Electronics","price":"137.87","rev1":"128181172311","rev2":"98139930360","rev3":"84303856969","rev4":"92357844418","lastEarningsFiscalQuarter":null},{"id":5,"symbol":"AMZN","companyName":"Amazon.com, Inc.","exchangeShortName":"NASDAQ","marketCap":"992115359744","sector":"Consumer Cyclical","industry":"Internet Retail","price":"97.25","rev1":"132353976070","rev2":"140897215012","rev3":"119692995554","rev4":"121356678614","lastEarningsFiscalQuarter":null},{"id":2,"symbol":"MSFT","companyName":"Microsoft Corporation","exchangeShortName":"NASDAQ","marketCap":"1790712872960","sector":"Technology","industry":"Software—Infrastructure","price":"240.22","rev1":"51943162902","rev2":"52997720097","rev3":"50385828892","rev4":"52337589170","lastEarningsFiscalQuarter":null}]