[{"id":1,"symbol":"AAPL","companyName":"Apple Inc.","exchangeShortName":"NASDAQ","marketCap":"2371131801600","sector":"Technology","industry":"Consumer Electronics","price":"146.5","rev1":"128011581408","rev2":"98878655676","rev3":"83408495061","rev4":"124226758742","lastEarningsFiscalQuarter":null},{"id":2,"symbol":"MSFT","companyName":"Microsoft Corporation","exchangeShortName":"NASDAQ","marketCap":"1948661055488","sector":"Technology","industry":"Software—Infrastructure","price":"260.55","rev1":"52202146748","rev2":"46690394115","rev3":"50133102603","rev4":"47258387537","lastEarningsFiscalQuarter":null},{"id":8,"symbol":"TSLA","companyName":"Tesla, Inc.","exchangeShortName":"NASDAQ","marketCap":"760431312896","sector":"Consumer Cyclical","industry":"Auto Manufacturers","price":"734","rev1":"18395870620","rev2":"18145516189","rev3":"12459228440","rev4":"14163083586","lastEarningsFiscalQuarter":null}]