[{"id":1,"symbol":"AAPL","companyName":"Apple Inc.","exchangeShortName":"NASDAQ","marketCap":"2757186813952","sector":"Technology","industry":"Consumer Electronics","price":"171.565","rev1":"126266798509","rev2":"125970342100","rev3":"87075181871","rev4":"98758195483","lastEarningsFiscalQuarter":null},{"id":5,"symbol":"AMZN","companyName":"Amazon.com, Inc.","exchangeShortName":"NASDAQ","marketCap":"1447607009280","sector":"Consumer Cyclical","industry":"Internet Retail","price":"142.095","rev1":"116106875646","rev2":"137474189606","rev3":"125908426576","rev4":"119367397509","lastEarningsFiscalQuarter":null},{"id":2,"symbol":"MSFT","companyName":"Microsoft Corporation","exchangeShortName":"NASDAQ","marketCap":"2168194990080","sector":"Technology","industry":"Software—Infrastructure","price":"290.725","rev1":"49821694705","rev2":"47346462132","rev3":"53109896978","rev4":"52272740134","lastEarningsFiscalQuarter":null},{"id":6,"symbol":"TSLA","companyName":"Tesla, Inc.","exchangeShortName":"NASDAQ","marketCap":"937429762048","sector":"Consumer Cyclical","industry":"Auto Manufacturers","price":"897.5","rev1":"14009688290","rev2":"17103044298","rev3":"18174849016","rev4":"18186232442","lastEarningsFiscalQuarter":null}]