[{"id":1,"symbol":"AAPL","companyName":"Apple Inc.","exchangeShortName":"NASDAQ","marketCap":"2816491388928","sector":"Technology","industry":"Consumer Electronics","price":"175.255","rev1":"124858593698","rev2":"86728620591","rev3":"124997109880","rev4":"98542524831","lastEarningsFiscalQuarter":null},{"id":5,"symbol":"AMZN","companyName":"Amazon.com, Inc.","exchangeShortName":"NASDAQ","marketCap":"1452518408192","sector":"Consumer Cyclical","industry":"Internet Retail","price":"142.577","rev1":"139047844586","rev2":"111858936769","rev3":"125319958353","rev4":"119009752489","lastEarningsFiscalQuarter":null},{"id":2,"symbol":"MSFT","companyName":"Microsoft Corporation","exchangeShortName":"NASDAQ","marketCap":"2180463198208","sector":"Technology","industry":"Software—Infrastructure","price":"292.37","rev1":"47556501474","rev2":"49889286202","rev3":"52608635467","rev4":"52314809188","lastEarningsFiscalQuarter":null},{"id":6,"symbol":"TSLA","companyName":"Tesla, Inc.","exchangeShortName":"NASDAQ","marketCap":"963291054080","sector":"Consumer Cyclical","industry":"Auto Manufacturers","price":"922.26","rev1":"17271329109","rev2":"14409650493","rev3":"18161327027","rev4":"18453340045","lastEarningsFiscalQuarter":null}]