[{"id":1,"symbol":"AAPL","companyName":"Apple Inc.","exchangeShortName":"NASDAQ","marketCap":"2129324802048","sector":"Technology","industry":"Consumer Electronics","price":"131.56","rev1":"125556265281","rev2":"99353890133","rev3":"83916706606","rev4":"127232812713","lastEarningsFiscalQuarter":null},{"id":5,"symbol":"AMZN","companyName":"Amazon.com, Inc.","exchangeShortName":"NASDAQ","marketCap":"1080724815872","sector":"Consumer Cyclical","industry":"Internet Retail","price":"106.22","rev1":"113412883534","rev2":"115173550210","rev3":"138303346140","rev4":"118588010392","lastEarningsFiscalQuarter":null},{"id":2,"symbol":"MSFT","companyName":"Microsoft Corporation","exchangeShortName":"NASDAQ","marketCap":"1852181708800","sector":"Technology","industry":"Software—Infrastructure","price":"247.65","rev1":"45712286791","rev2":"49445531401","rev3":"48027147538","rev4":"53214862048","lastEarningsFiscalQuarter":null}]