[{"id":2,"symbol":"AAPL","companyName":"Apple Inc.","exchangeShortName":"NASDAQ","marketCap":"2708482211635","sector":"Technology","industry":"Consumer Electronics","price":"172.2","rev1":"86837474507","rev2":"120299468221","rev3":"91998568761","rev4":"96095756111","lastEarningsFiscalQuarter":null},{"id":7,"symbol":"AMZN","companyName":"Amazon.com, Inc.","exchangeShortName":"NASDAQ","marketCap":"1168660600619","sector":"Consumer Cyclical","industry":"Internet Retail","price":"113.9001","rev1":"132740557056","rev2":"121281214262","rev3":"155837284530","rev4":"133556823999","lastEarningsFiscalQuarter":null},{"id":3,"symbol":"MSFT","companyName":"Microsoft Corporation","exchangeShortName":"NASDAQ","marketCap":"2324185399183","sector":"Technology","industry":"Software—Infrastructure","price":"312.58","rev1":"51503676156","rev2":"53852711898","rev3":"52973993446","rev4":"54822558919","lastEarningsFiscalQuarter":null},{"id":10,"symbol":"NVDA","companyName":"NVIDIA Corporation","exchangeShortName":"NASDAQ","marketCap":"731329267569","sector":"Technology","industry":"Semiconductors","price":"295.71","rev1":"8642813965","rev2":"6262807410","rev3":"6927169870","rev4":"6136808889","lastEarningsFiscalQuarter":null},{"id":14,"symbol":"TSLA","companyName":"Tesla, Inc.","exchangeShortName":"NASDAQ","marketCap":"529670976457","sector":"Consumer Cyclical","industry":"Auto Manufacturers","price":"167.115","rev1":"16976052360","rev2":"22091929585","rev3":"24614380913","rev4":"23386199014","lastEarningsFiscalQuarter":null}]