[{"id":2,"symbol":"AAPL","companyName":"Apple Inc.","exchangeShortName":"NASDAQ","marketCap":"2382619887268","sector":"Technology","industry":"Consumer Electronics","price":"150.59","rev1":"85983359714","rev2":"101836857722","rev3":"121390792961","rev4":"92997863410","lastEarningsFiscalQuarter":null},{"id":7,"symbol":"AMZN","companyName":"Amazon.com, Inc.","exchangeShortName":"NASDAQ","marketCap":"945313433856","sector":"Consumer Cyclical","industry":"Internet Retail","price":"92.25","rev1":"124984030022","rev2":"129545524729","rev3":"119304449302","rev4":"150403643895","lastEarningsFiscalQuarter":null},{"id":3,"symbol":"MSFT","companyName":"Microsoft Corporation","exchangeShortName":"NASDAQ","marketCap":"1878219632148","sector":"Technology","industry":"Software—Infrastructure","price":"252.32","rev1":"52825331614","rev2":"52980225373","rev3":"52354314598","rev4":"49686818756","lastEarningsFiscalQuarter":null},{"id":13,"symbol":"NVDA","companyName":"NVIDIA Corporation","exchangeShortName":"NASDAQ","marketCap":"584025120000","sector":"Technology","industry":"Semiconductors","price":"234.36","rev1":"6346801329","rev2":"8508894504","rev3":"6908114091","rev4":"6088507514","lastEarningsFiscalQuarter":null},{"id":14,"symbol":"TSLA","companyName":"Tesla, Inc.","exchangeShortName":"NASDAQ","marketCap":"547136188600","sector":"Consumer Cyclical","industry":"Auto Manufacturers","price":"172.92","rev1":"21207505035","rev2":"18493494902","rev3":"16783690609","rev4":"24509773056","lastEarningsFiscalQuarter":null}]