[
  {
    "symbol": "BAC-PL",
    "companyName": "Bank of America Corporation",
    "marketCap": 9110447499115,
    "sector": "Financial Services",
    "industry": "Banks—Diversified",
    "beta": 1.41424,
    "price": 1130.5,
    "lastAnnualDividend": 72.5,
    "volume": 15282,
    "exchange": "New York Stock Exchange",
    "exchangeShortName": "NYSE",
    "country": "US",
    "isEtf": false,
    "isActivelyTrading": true
  },
  {
    "symbol": "AAPL",
    "companyName": "Apple Inc.",
    "marketCap": 2489575929754,
    "sector": "Technology",
    "industry": "Consumer Electronics",
    "beta": 1.297088,
    "price": 157.35,
    "lastAnnualDividend": 0.92,
    "volume": 50600373,
    "exchange": "NASDAQ Global Select",
    "exchangeShortName": "NASDAQ",
    "country": "US",
    "isEtf": false,
    "isActivelyTrading": true
  },
  {
    "symbol": "MSFT",
    "companyName": "Microsoft Corporation",
    "marketCap": 2017790883348,
    "sector": "Technology",
    "industry": "Software—Infrastructure",
    "beta": 0.915117,
    "price": 271.07,
    "lastAnnualDividend": 2.72,
    "volume": 31971529,
    "exchange": "NASDAQ Global Select",
    "exchangeShortName": "NASDAQ",
    "country": "US",
    "isEtf": false,
    "isActivelyTrading": true
  },
  {
    "symbol": "GOOG",
    "companyName": "Alphabet Inc.",
    "marketCap": 1303397060252,
    "sector": "Communication Services",
    "industry": "Internet Content & Information",
    "beta": 1.090845,
    "price": 102.22,
    "lastAnnualDividend": 0,
    "volume": 17975647,
    "exchange": "NASDAQ Global Select",
    "exchangeShortName": "NASDAQ",
    "country": "US",
    "isEtf": false,
    "isActivelyTrading": true
  },
  {
    "symbol": "GOOGL",
    "companyName": "Alphabet Inc.",
    "marketCap": 1303114507488,
    "sector": "Communication Services",
    "industry": "Internet Content & Information",
    "beta": 1.090845,
    "price": 101.36,
    "lastAnnualDividend": 0,
    "volume": 22999952,
    "exchange": "NASDAQ Global Select",
    "exchangeShortName": "NASDAQ",
    "country": "US",
    "isEtf": false,
    "isActivelyTrading": true
  },
  {
    "symbol": "USB-PA",
    "companyName": "U.S. Bancorp PERP PFD SER A",
    "marketCap": 1291877054521,
    "sector": "",
    "industry": null,
    "beta": 0,
    "price": 769.4599,
    "lastAnnualDividend": 39.65458,
    "volume": 2200,
    "exchange": "New York Stock Exchange",
    "exchangeShortName": "NYSE",
    "country": null,
    "isEtf": false,
    "isActivelyTrading": true
  },
  {
    "symbol": "AMZN",
    "companyName": "Amazon.com, Inc.",
    "marketCap": 995371494825,
    "sector": "Consumer Cyclical",
    "industry": "Internet Retail",
    "beta": 1.253595,
    "price": 97.135,
    "lastAnnualDividend": 0.2,
    "volume": 47823562,
    "exchange": "NASDAQ Global Select",
    "exchangeShortName": "NASDAQ",
    "country": "US",
    "isEtf": false,
    "isActivelyTrading": true
  },
  {
    "symbol": "DHR-PB",
    "companyName": "Danaher Corporation",
    "marketCap": 897305228214,
    "sector": "Healthcare",
    "industry": "Diagnostics & Research",
    "beta": 0.802174,
    "price": 1234.5,
    "lastAnnualDividend": 50,
    "volume": 14943,
    "exchange": "New York Stock Exchange",
    "exchangeShortName": "NYSE",
    "country": "US",
    "isEtf": false,
    "isActivelyTrading": true
  },
  {
    "symbol": "VITSX",
    "companyName": "Vanguard Total Stock Market Index Fund",
    "marketCap": 804653105118,
    "sector": "",
    "industry": null,
    "beta": 0,
    "price": 95.02,
    "lastAnnualDividend": 1.55,
    "volume": 0,
    "exchange": "Nasdaq",
    "exchangeShortName": "NASDAQ",
    "country": "US",
    "isEtf": false,
    "isActivelyTrading": true
  },
  {
    "symbol": "VTSAX",
    "companyName": "Vanguard Total Stock Market Index Fund",
    "marketCap": 804483760070,
    "sector": "",
    "industry": null,
    "beta": 0,
    "price": 95,
    "lastAnnualDividend": 1.54,
    "volume": 0,
    "exchange": "Nasdaq",
    "exchangeShortName": "NASDAQ",
    "country": "US",
    "isEtf": false,
    "isActivelyTrading": true
  },
  {
    "symbol": "BRK-A",
    "companyName": "Berkshire Hathaway Inc.",
    "marketCap": 679796817968,
    "sector": "Financial Services",
    "industry": "Insurance—Diversified",
    "beta": 0.881795,
    "price": 454680.44,
    "lastAnnualDividend": 0,
    "volume": 5873,
    "exchange": "New York Stock Exchange",
    "exchangeShortName": "NYSE",
    "country": "US",
    "isEtf": false,
    "isActivelyTrading": true
  },
  {
    "symbol": "BRK-B",
    "companyName": "Berkshire Hathaway Inc.",
    "marketCap": 657497721413,
    "sector": "Financial Services",
    "industry": "Insurance—Diversified",
    "beta": 0.881795,
    "price": 299.9,
    "lastAnnualDividend": 0,
    "volume": 3352755,
    "exchange": "New York Stock Exchange",
    "exchangeShortName": "NYSE",
    "country": "US",
    "isEtf": false,
    "isActivelyTrading": true
  },
  {
    "symbol": "NVDA",
    "companyName": "NVIDIA Corporation",
    "marketCap": 645677200000,
    "sector": "Technology",
    "industry": "Semiconductors",
    "beta": 1.757278,
    "price": 259.1,
    "lastAnnualDividend": 0.16,
    "volume": 35196625,
    "exchange": "NASDAQ Global Select",
    "exchangeShortName": "NASDAQ",
    "country": "US",
    "isEtf": false,
    "isActivelyTrading": true
  },
  {
    "symbol": "TSLA",
    "companyName": "Tesla, Inc.",
    "marketCap": 580311778107,
    "sector": "Consumer Cyclical",
    "industry": "Auto Manufacturers",
    "beta": 2.070501,
    "price": 183.405,
    "lastAnnualDividend": 0,
    "volume": 115536188,
    "exchange": "NASDAQ Global Select",
    "exchangeShortName": "NASDAQ",
    "country": "US",
    "isEtf": false,
    "isActivelyTrading": true
  },
  {
    "symbol": "META",
    "companyName": "Meta Platforms, Inc.",
    "marketCap": 536742358443,
    "sector": "Communication Services",
    "industry": "Internet Content & Information",
    "beta": 1.179936,
    "price": 197.61,
    "lastAnnualDividend": 0,
    "volume": 19406772,
    "exchange": "NASDAQ Global Select",
    "exchangeShortName": "NASDAQ",
    "country": "US",
    "isEtf": false,
    "isActivelyTrading": true
  }
]
